LICENSE
MANIFEST.in
README.rst
pyproject.toml
setup.cfg
setup.py
photoeccentric/__init__.py
photoeccentric/eccentricity.py
photoeccentric/lcfitter.py
photoeccentric/photoeccentric.py
photoeccentric/stellardensity.py
photoeccentric/utils.py
photoeccentric.egg-info/PKG-INFO
photoeccentric.egg-info/SOURCES.txt
photoeccentric.egg-info/dependency_links.txt
photoeccentric.egg-info/not-zip-safe
photoeccentric.egg-info/requires.txt
photoeccentric.egg-info/top_level.txt