Metadata-Version: 2.1
Name: photoeccentric
Version: 0.2
Summary: Photoeccentric
Home-page: https://link-to-your-project
Author: Sheila Sagear
Author-email: Sheila Sagear <ssagear@ufl.edu>
License: MIT
License-File: LICENSE
Requires-Dist: numpy
Requires-Dist: astropy
Requires-Dist: matplotlib
Requires-Dist: tqdm
Requires-Dist: emcee
Requires-Dist: corner
Requires-Dist: batman-package
Requires-Dist: juliet
